{
  "post": {
    "url": "https://twitter.com/baschtdotcom/status/1336584252142592000",
    "name": null,
    "type": "entry",
    "wm-id": 942711,
    "author": {
      "url": "https://twitter.com/baschtdotcom",
      "name": "bascht.com",
      "type": "card",
      "photo": "https://webmention.io/avatar/pbs.twimg.com/c9394c89bf268b18fb0a80cf75bcc9b8b7306b45c87eb687eff23cf0844b3d93.png"
    },
    "content": {
      "html": "bascht: “🏃”… • <a href=\"https://bascht.com/posts/2020/12/09/bascht/\">bascht.com/posts/2020/12/…</a>",
      "text": "bascht: “🏃”… • bascht.com/posts/2020/12/…"
    },
    "published": "2020-12-09T08:11:32+00:00",
    "wm-source": "https://brid-gy.appspot.com/post/twitter/bascht/1336584252142592000",
    "wm-target": "https://bascht.com/posts/2020/12/09/bascht/",
    "wm-private": false,
    "in-reply-to": null,
    "wm-property": "mention-of",
    "wm-received": "2020-12-09T08:42:24Z"
  },
  "secret": null,
  "source": "https://brid-gy.appspot.com/post/twitter/bascht/1336584252142592000",
  "target": "https://bascht.com/posts/2020/12/09/bascht/",
  "private": false
}