{
  "post": {
    "url": "https://social.yakshed.org/@bascht/107140490562368940#favorited-by-4618",
    "name": null,
    "type": "entry",
    "wm-id": 1294784,
    "author": {
      "url": "https://bonn.social/@vilbi",
      "name": "Wolfgang",
      "type": "card",
      "photo": "https://webmention.io/avatar/sb-yakshed.b-cdn.net/ff8c6162ccd03b592ea8277d4fb8c8a3dce788e7f8d503357feeaf5ee9c81691.png"
    },
    "content": {
      "html": null,
      "text": null
    },
    "published": null,
    "wm-source": "https://brid.gy/like/mastodon/@bascht@social.yakshed.org/107140490562368940/4618",
    "wm-target": "https://bascht.com/posts/2021/10/21/bascht-fahre/",
    "wm-private": false,
    "in-reply-to": null,
    "wm-property": "like-of",
    "wm-received": "2021-10-21T19:50:50Z"
  },
  "secret": null,
  "source": "https://brid.gy/like/mastodon/@bascht@social.yakshed.org/107140490562368940/4618",
  "target": "https://bascht.com/posts/2021/10/21/bascht-fahre/",
  "private": false
}