{
  "post": {
    "url": "https://twitter.com/bascht/status/1336211852666212357#favorited-by-51193",
    "name": null,
    "type": "entry",
    "wm-id": 942009,
    "author": {
      "url": "https://twitter.com/til",
      "name": "til",
      "type": "card",
      "photo": "https://webmention.io/avatar/pbs.twimg.com/7cc0b0e9ddc1a57061cd7bf1ac91a0b673558d3fc7aea980c3b5ee361ab838b9.jpg"
    },
    "content": {
      "html": null,
      "text": null
    },
    "published": null,
    "wm-source": "https://brid-gy.appspot.com/like/twitter/bascht/1336211852666212357/51193",
    "wm-target": "https://bascht.com/posts/2020/12/08/kratzt-ihr-mal.-ich-fahr-schon-los.-%EF%B8%8F-h/",
    "wm-private": false,
    "in-reply-to": null,
    "wm-property": "like-of",
    "wm-received": "2020-12-08T18:42:32Z"
  },
  "secret": null,
  "source": "https://brid-gy.appspot.com/like/twitter/bascht/1336211852666212357/51193",
  "target": "https://bascht.com/posts/2020/12/08/kratzt-ihr-mal.-ich-fahr-schon-los.-%EF%B8%8F-h/",
  "private": false
}