{
  "post": {
    "url": "https://social.yakshed.org/@bascht/106051919441494934#favorited-by-4841",
    "name": null,
    "type": "entry",
    "wm-id": 1122646,
    "author": {
      "url": "https://social.coop/@edsu",
      "name": "Ed Summers",
      "type": "card",
      "photo": "https://webmention.io/avatar/sb-yakshed.b-cdn.net/578862cd6c2e166318ff52282b598d046422efd82c65feee5c7c95c7bf526dff.jpg"
    },
    "content": {
      "html": null,
      "text": null
    },
    "published": null,
    "wm-source": "https://brid.gy/like/mastodon/@bascht@social.yakshed.org/106051919441494934/4841",
    "wm-target": "https://bascht.com/posts/2021/04/12/french-mps-have-voted-to-suspend-domesti/",
    "wm-private": false,
    "in-reply-to": null,
    "wm-property": "like-of",
    "wm-received": "2021-04-15T23:37:46Z"
  },
  "secret": null,
  "source": "https://brid.gy/like/mastodon/@bascht@social.yakshed.org/106051919441494934/4841",
  "target": "https://bascht.com/posts/2021/04/12/french-mps-have-voted-to-suspend-domesti/",
  "private": false
}