{
  "post": {
    "url": "https://social.yakshed.org/@bascht/106059264980700089",
    "name": null,
    "type": "entry",
    "wm-id": 1120988,
    "author": {
      "url": "https://social.yakshed.org/@bascht",
      "name": "Bascht",
      "type": "card",
      "photo": "https://webmention.io/avatar/sb-yakshed.b-cdn.net/c38d71338cbad383865d4cd6aa7cdf8f8b5d3e8b412af6ab8e02e9c8b1506812.jpg"
    },
    "content": {
      "html": "<p><span class=\"h-card\"><a href=\"https://social.tchncs.de/@michiel\" class=\"u-url\">@<span>michiel</span></a></span> I wonder how Berlin -&gt; Munich ranks after Deutsche Bahn opened up the new route via Erfurt, cutting travel time down to about 4.5h. I used to commute via train in 2015 and it was aweful (7~ish hours).</p>",
      "text": "@michiel I wonder how Berlin -> Munich ranks after Deutsche Bahn opened up the new route via Erfurt, cutting travel time down to about 4.5h. I used to commute via train in 2015 and it was aweful (7~ish hours)."
    },
    "published": "2021-04-13T17:45:52",
    "wm-source": "https://brid.gy/comment/mastodon/@bascht@social.yakshed.org/106051919441494934/106059264980700089",
    "wm-target": "https://bascht.com/posts/2021/04/12/french-mps-have-voted-to-suspend-domesti/",
    "wm-private": false,
    "in-reply-to": "https://bascht.com/posts/2021/04/12/french-mps-have-voted-to-suspend-domesti/",
    "wm-property": "in-reply-to",
    "wm-received": "2021-04-15T00:18:53Z"
  },
  "secret": null,
  "source": "https://brid.gy/comment/mastodon/@bascht@social.yakshed.org/106051919441494934/106059264980700089",
  "target": "https://bascht.com/posts/2021/04/12/french-mps-have-voted-to-suspend-domesti/",
  "private": false
}