{
  "post": {
    "url": "https://social.yakshed.org/@bascht/108253605128721652#favorited-by-108236207186059478",
    "name": null,
    "type": "entry",
    "wm-id": 1392957,
    "author": {
      "url": "https://mastodon.green/@bitboxer",
      "name": "Bodo",
      "type": "card",
      "photo": "https://webmention.io/avatar/sb-yakshed.b-cdn.net/e3d9345802d1c4c56140b3d34a933c543853c322d4db3c1b4b6b722407697f00.jpg"
    },
    "content": {
      "html": null,
      "text": null
    },
    "published": null,
    "wm-source": "https://brid.gy/like/mastodon/@bascht@social.yakshed.org/108253605128721652/108236207186059478",
    "wm-target": "https://bascht.com/posts/2022/05/06/bascht-neat-dedicated-scooter-spaces/",
    "wm-private": false,
    "in-reply-to": null,
    "wm-property": "like-of",
    "wm-received": "2022-05-06T13:28:13Z"
  },
  "secret": null,
  "source": "https://brid.gy/like/mastodon/@bascht@social.yakshed.org/108253605128721652/108236207186059478",
  "target": "https://bascht.com/posts/2022/05/06/bascht-neat-dedicated-scooter-spaces/",
  "private": false
}