{
  "post": {
    "url": "https://social.yakshed.org/@bascht/107439904263809056#favorited-by-76715",
    "name": null,
    "type": "entry",
    "wm-id": 1316020,
    "author": {
      "url": "https://mastodon.lol/@elleread",
      "name": "typhoooooon",
      "type": "card",
      "photo": "https://webmention.io/avatar/sb-yakshed.b-cdn.net/8ed1c8fe46831dbb757725941aa4da81bc6cf4c2f883bb59fcd1b646f5579dfd.png"
    },
    "content": {
      "html": null,
      "text": null
    },
    "published": null,
    "wm-source": "https://brid.gy/like/mastodon/@bascht@social.yakshed.org/107439904263809056/76715",
    "wm-target": "https://bascht.com/posts/2021/12/13/bascht-hej-fediverse-boosts-apprecia/",
    "wm-private": false,
    "in-reply-to": null,
    "wm-property": "like-of",
    "wm-received": "2021-12-13T18:15:42Z"
  },
  "secret": null,
  "source": "https://brid.gy/like/mastodon/@bascht@social.yakshed.org/107439904263809056/76715",
  "target": "https://bascht.com/posts/2021/12/13/bascht-hej-fediverse-boosts-apprecia/",
  "private": false
}