{
  "post": {
    "url": "https://www.instagram.com/p/CCVuCWin_qy/#liked-by-3645537",
    "name": null,
    "type": "entry",
    "wm-id": 821677,
    "author": {
      "url": "https://www.instagram.com/the_vegan_valkyrie/",
      "name": "the_vegan_valkyrie",
      "type": "card",
      "photo": "https://webmention.io/avatar/scontent-iad3-1.cdninstagram.com/816bdfff8ac6231c1d111e178f6391333e77c9e09a4599e9c67f93242a1a2f05.jpg"
    },
    "content": {
      "html": null,
      "text": null
    },
    "published": null,
    "wm-source": "https://brid-gy.appspot.com/like/instagram/bascht/2347985252525275826_31971527/3645537",
    "wm-target": "https://bascht.com/posts/2020/07/07/hi/",
    "wm-private": false,
    "in-reply-to": null,
    "wm-property": "like-of",
    "wm-received": "2020-07-08T19:13:37Z"
  },
  "secret": null,
  "source": "https://brid-gy.appspot.com/like/instagram/bascht/2347985252525275826_31971527/3645537",
  "target": "https://bascht.com/posts/2020/07/07/hi/",
  "private": false
}
